{
  "R550" : "R550",
  "Place Vendome EDP" : "Place Vendome EDP",
  "Pack Of 3 Pure Linen Air Freshner Card" : "Pack Of 3 Pure Linen Air Freshner Card",
  "Premium Slim Snap Case Cover Matte Finish for Apple iPhone 6/6s" : "Premium Slim Snap Case Cover Matte Finish for Apple iPhone 6/6s",
  "Slim Snap Case Cover - Diverge for OnePlus OnePlus 3/3T" : "Slim Snap Case Cover - Diverge for OnePlus OnePlus 3/3T",
  "Premium Vinyl Skin Decal Body Wrap for Samsung Galaxy Note 4" : "Premium Vinyl Skin Decal Body Wrap for Samsung Galaxy Note 4",
  "Premium Vinyl Skin Decal Body Wrap for Samsung Galaxy Note 5" : "Premium Vinyl Skin Decal Body Wrap for Samsung Galaxy Note 5",
  "Premium Vinyl Skin Decal Body Wrap for Samsung Galaxy Note 7" : "Premium Vinyl Skin Decal Body Wrap for Samsung Galaxy Note 7",
  "Premium Vinyl Skin Decal Body Wrap for Samsung Galaxy Note 3" : "Premium Vinyl Skin Decal Body Wrap for Samsung Galaxy Note 3",
  "Slim Snap Case Cover - Angry Birds for Huawei Honor 6 Plus" : "Slim Snap Case Cover - Angry Birds for Huawei Honor 6 Plus",
  "SL.9.872.1.Y6 Analog Display Leather Band Watch" : "SL.9.872.1.Y6 Analog Display Leather Band Watch",
  "Pack Of 3 Island Retreat Air Freshner Card" : "Pack Of 3 Island Retreat Air Freshner Card",
  "Oxford Sleek Casual Brass Watch - MOX-0109" : "Oxford Sleek Casual Brass Watch - MOX-0109",
  "Premium Slim Snap Case Cover for Apple iPhone 5/5s/SE" : "Premium Slim Snap Case Cover for Apple iPhone 5/5s/SE",
  "ROG 17.3-Inch Display, Core i7 Processor/8GBRAM/1TB HDD/4GB NVIDIA Graphic Card" : "ROG 17.3-Inch Display, Core i7 Processor/8GBRAM/1TB HDD/4GB NVIDIA Graphic Card",
  "Quatre Limited Edition EDP" : "Quatre Limited Edition EDP",
  "Pack Of 3 Mount Air Air Freshner Card" : "Pack Of 3 Mount Air Air Freshner Card",
  "Oros Holiday Edition EDP" : "Oros Holiday Edition EDP",
  "Side Flip Leather Case For Samsung Galaxy S3" : "Side Flip Leather Case For Samsung Galaxy S3",
  "SL.9.1353 Multi Function Leather Band Watch" : "SL.9.1353 Multi Function Leather Band Watch",
  "Signorina Eleganza EDP Set" : "Signorina Eleganza EDP Set",
  "SL.9.917.2.J7 Chronograph Display Leather Band Watch" : "SL.9.917.2.J7 Chronograph Display Leather Band Watch",
  "Rosemary Jamaican Black Castor Oil" : "Rosemary Jamaican Black Castor Oil",
  "Opus Series Alloy Watch - LO-OM-II-0709" : "Opus Series Alloy Watch - LO-OM-II-0709",
  "Pack Of 3 Star Ball 40+" : "Pack Of 3 Star Ball 40+",
  "Quatre Limited Edition Edition EDP" : "Quatre Limited Edition Edition EDP",
  "Premium Vinyl Skin Decal Body Wrap for Apple iPad Air 2" : "Premium Vinyl Skin Decal Body Wrap for Apple iPad Air 2",
  "Premium Vinyl Skin Decal Body Wrap for Apple iPhone 4s" : "Premium Vinyl Skin Decal Body Wrap for Apple iPhone 4s",
  "Slim Snap Case Cover for Samsung Galaxy A5 2016" : "Slim Snap Case Cover for Samsung Galaxy A5 2016",
  "Portable Power Bank" : "Portable Power Bank",
  "Raw Shea Butter Restorative Conditioner" : "Raw Shea Butter Restorative Conditioner",
  "Premium Vinyl Skin Decal Body Wrap for LG G3 D855" : "Premium Vinyl Skin Decal Body Wrap for LG G3 D855",
  "Slim Snap Case Cover - Tibute - Bruce Lee for Samsung Galaxy A3 2016" : "Slim Snap Case Cover - Tibute - Bruce Lee for Samsung Galaxy A3 2016",
  "Rosemary Jamaican Black Castor Oil Hair Pomade" : "Rosemary Jamaican Black Castor Oil Hair Pomade",
  "SL.9.853.4.06 Multi Function Display Stainless Steel Band Watch" : "SL.9.853.4.06 Multi Function Display Stainless Steel Band Watch",
  "Slim Snap Case Cover for Huawei Honor 5X" : "Slim Snap Case Cover for Huawei Honor 5X",
  "Safron Rare EDP" : "Safron Rare EDP",
  "Ricci Mademoiselle Ricci EDP" : "Ricci Mademoiselle Ricci EDP",
  "Silicon Straped Outlander III Watch - LO-OTR-III-0202" : "Silicon Straped Outlander III Watch - LO-OTR-III-0202",
  "Slim Snap Case Cover Matte Finish for Sony Xperia Z3" : "Slim Snap Case Cover Matte Finish for Sony Xperia Z3",
  "Premium Vinyl Skin Decal Body Wrap for Huawei P9 Plus" : "Premium Vinyl Skin Decal Body Wrap for Huawei P9 Plus",
  "Premium Slim Snap Case Cover Matte Finish for Sony Xperia Z3 Plus" : "Premium Slim Snap Case Cover Matte Finish for Sony Xperia Z3 Plus",
  "Retractable Ratchet Strap 3m" : "Retractable Ratchet Strap 3m",
  "Oud Et Santal EDP" : "Oud Et Santal EDP",
  "Real Madrid Football Club Shoulder Bag For iPad And All Other Tablets" : "Real Madrid Football Club Shoulder Bag For iPad And All Other Tablets",
  "Orchid Roman Fabric Watch - LO-ORC-030307" : "Orchid Roman Fabric Watch - LO-ORC-030307",
  "Rise EDP" : "Rise EDP",
  "Rose Noir EDP" : "Rose Noir EDP",
  "Sicily EDP" : "Sicily EDP",
  "Premium Flip Case Cover for Apple iPhone 6 Plus" : "Premium Flip Case Cover for Apple iPhone 6 Plus",
  "Slim Snap Case Cover - Gameboy Colours for Samsung Galaxy A5 2016" : "Slim Snap Case Cover - Gameboy Colours for Samsung Galaxy A5 2016",
  "Slim Snap Case Cover Matte Finish for Sony Xperia Z5 Premium" : "Slim Snap Case Cover Matte Finish for Sony Xperia Z5 Premium",
  "Slim Snap Case Cover - Street Fighter - Ken for OnePlus OnePlus 3/3T" : "Slim Snap Case Cover - Street Fighter - Ken for OnePlus OnePlus 3/3T",
  "Signorina In Fiore EDT Gift Set" : "Signorina In Fiore EDT Gift Set",
  "Secret Amber Romance Body Mist" : "Secret Amber Romance Body Mist",
  "Premium Slim Snap Case Cover Gloss Finish for Samsung Galaxy S6 Edge" : "Premium Slim Snap Case Cover Gloss Finish for Samsung Galaxy S6 Edge",
  "Ratchet Tie Down J Hooks 8.25m" : "Ratchet Tie Down J Hooks 8.25m",
  "Rachet Tie Down S Hooks 5m" : "Rachet Tie Down S Hooks 5m",
  "Oud Woody" : "Oud Woody",
  "Rose EDP" : "Rose EDP",
  "Premium Flip Case Cover for Apple iPhone 6" : "Premium Flip Case Cover for Apple iPhone 6",
  "SL.9.955.3.05 Analog Display Ceramic Band Watch" : "SL.9.955.3.05 Analog Display Ceramic Band Watch",
  "Pour Femme EDP Set" : "Pour Femme EDP Set",
  "Premium Vinyl Skin Decal Body Wrap for Nokia Lumia 900" : "Premium Vinyl Skin Decal Body Wrap for Nokia Lumia 900",
  "Slim Snap Case Cover - Keep Calm And Eat Shawarma for Samsung Galaxy A5 2016" : "Slim Snap Case Cover - Keep Calm And Eat Shawarma for Samsung Galaxy A5 2016",
  "Slim Snap Case Cover Matte Finish for Sony Xperia Z3 Plus" : "Slim Snap Case Cover Matte Finish for Sony Xperia Z3 Plus",
  "Platinum Egoiste EDT Spray" : "Platinum Egoiste EDT Spray",
  "Premium Vinyl Skin Decal Body Wrap for Blackberry Z10" : "Premium Vinyl Skin Decal Body Wrap for Blackberry Z10",
  "Premium Vinyl Skin Decal Body Wrap for Google Nexus 6P" : "Premium Vinyl Skin Decal Body Wrap for Google Nexus 6P",
  "Premium Dual Layer Tough Case for Apple iPhone 6" : "Premium Dual Layer Tough Case for Apple iPhone 6",
  "Premium Wash 48oz" : "Premium Wash 48oz",
  "Pure Art EDP In Wooden Box" : "Pure Art EDP In Wooden Box",
  "SL.9.853.4.05 Multi Function Display Stainless Steel Band Watch" : "SL.9.853.4.05 Multi Function Display Stainless Steel Band Watch",
  "Premium Vinyl Skin Decal Body Wrap for Lenovo K5 Note" : "Premium Vinyl Skin Decal Body Wrap for Lenovo K5 Note",
  "Premium Dual Layer Tough Case Cover Gloss Finish for Apple iPhone 6 Plus" : "Premium Dual Layer Tough Case Cover Gloss Finish for Apple iPhone 6 Plus",
  "Quicksilver Wheel And Tyre Cleaner 24oz" : "Quicksilver Wheel And Tyre Cleaner 24oz",
  "Premium Dual Layer Tough Case Cover for Apple iPhone 5/5s" : "Premium Dual Layer Tough Case Cover for Apple iPhone 5/5s",
  "Premium Slim Snap Case Cover Matte Finish for Apple iPhone 6" : "Premium Slim Snap Case Cover Matte Finish for Apple iPhone 6",
  "Paris Florabotanica EDP" : "Paris Florabotanica EDP",
  "Premium Slim Snap Case Cover Matte Finish for Apple iPhone 6 Plus/6s Plus" : "Premium Slim Snap Case Cover Matte Finish for Apple iPhone 6 Plus/6s Plus",
  "SL.9.917.2.J1 Chronograph Display Leather Band Watch" : "SL.9.917.2.J1 Chronograph Display Leather Band Watch",
  "Slim Snap Case Cover - Gameboy Colour for Google Pixel XL" : "Slim Snap Case Cover - Gameboy Colour for Google Pixel XL",
  "Slim Snap Case Cover - Keep Calm And Eat Shawarma for Google Pixel XL" : "Slim Snap Case Cover - Keep Calm And Eat Shawarma for Google Pixel XL",
  "Premium Slim Snap Case Cover Gloss Finish for Apple iPhone 6 Plus/6s Plus" : "Premium Slim Snap Case Cover Gloss Finish for Apple iPhone 6 Plus/6s Plus",
  "Roses and Chocolaty EDP" : "Roses and Chocolaty EDP",
  "Paul Frank Monkey Picture Case For iPad Mini" : "Paul Frank Monkey Picture Case For iPad Mini",
  "Piguet Cravache EDT" : "Piguet Cravache EDT",
  "Shield Wax 500ml" : "Shield Wax 500ml",
  "Oxford Sleek Casual Brass Watch - MOX-0202" : "Oxford Sleek Casual Brass Watch - MOX-0202",
  "Piguet Gardenia EDP" : "Piguet Gardenia EDP",
  "Premium Dual Layer Tough Case Cover for Apple iPhone 5/5s/SE" : "Premium Dual Layer Tough Case Cover for Apple iPhone 5/5s/SE",
  "S16 Mobile Phone With 20000mAh Power Bank Battery" : "S16 Mobile Phone With 20000mAh Power Bank Battery",
  "Premium Analog Chain Watch - WL-0107" : "Premium Analog Chain Watch - WL-0107",
  "Oud Rose EDP" : "Oud Rose EDP",
  "Premium Vinyl Skin Decal Body Wrap for Samsung Galaxy S5 Mini" : "Premium Vinyl Skin Decal Body Wrap for Samsung Galaxy S5 Mini",
  "ROG 17.3-Inch Display, Core i7 Processor/24GBRAM/1TB+256GB SSD Hybrid Drive/8GB NVIDIA Graphic Card" : "ROG 17.3-Inch Display, Core i7 Processor/24GBRAM/1TB+256GB SSD Hybrid Drive/8GB NVIDIA Graphic Card",
  "Orchid Roman Fabric Watch - LO-ORC-040407" : "Orchid Roman Fabric Watch - LO-ORC-040407",
  "Slim Snap Case Cover - Keep Calm And Eat Shawarma for Google Pixel" : "Slim Snap Case Cover - Keep Calm And Eat Shawarma for Google Pixel",
  "Remote Control Racing Car" : "Remote Control Racing Car",
  "Pavilion 17t 17.3-Inch Display, Core i7 Processor/16GBRAM/1TB+128GB SSD Hybrid Drive/4GB NVIDIA Graphic Card" : "Pavilion 17t 17.3-Inch Display, Core i7 Processor/16GBRAM/1TB+128GB SSD Hybrid Drive/4GB NVIDIA Graphic Card",
  "Original Protectant 10oz" : "Original Protectant 10oz",
  "Premium Vinyl Skin Decal Body Wrap for OnePlus OnePlus X" : "Premium Vinyl Skin Decal Body Wrap for OnePlus OnePlus X",
  "Slim Snap Case Cover for Google Pixel XL" : "Slim Snap Case Cover for Google Pixel XL",
  "Portable Boombox 3.0 Music Bluetooth Double Speaker" : "Portable Boombox 3.0 Music Bluetooth Double Speaker",
  "Red Door 25th Anniver.EDP" : "Red Door 25th Anniver.EDP",
  "Sauvage EDT Mini Set" : "Sauvage EDT Mini Set",
  "Oud Et Rose EDP" : "Oud Et Rose EDP",
  "Premium Vinyl Skin Decal Body Wrap for Google Nexus 6" : "Premium Vinyl Skin Decal Body Wrap for Google Nexus 6",
  "Premium Vinyl Skin Decal Body Wrap for Motorola Moto X" : "Premium Vinyl Skin Decal Body Wrap for Motorola Moto X",
  "Premium Vinyl Skin Decal Body Wrap for OnePlus OnePlus 2" : "Premium Vinyl Skin Decal Body Wrap for OnePlus OnePlus 2",
  "Premium Vinyl Skin Decal Body Wrap for OnePlus OnePlus 3" : "Premium Vinyl Skin Decal Body Wrap for OnePlus OnePlus 3",
  "Slim Snap Case Cover for Huawei Honor 6 Plus" : "Slim Snap Case Cover for Huawei Honor 6 Plus",
  "Private Klub EDP" : "Private Klub EDP",
  "Premium Vinyl Skin Decal Body Wrap for Motorola Moto G" : "Premium Vinyl Skin Decal Body Wrap for Motorola Moto G",
  "Private Klub EDT" : "Private Klub EDT",
  "Slim Snap Case Cover - I Love Pizza for Google Pixel XL" : "Slim Snap Case Cover - I Love Pizza for Google Pixel XL",
  "Premium Vinyl Skin Decal Body Wrap for Apple iPhone 5c" : "Premium Vinyl Skin Decal Body Wrap for Apple iPhone 5c",
  "Rush 2 EDT" : "Rush 2 EDT",
  "Premium Slim Snap Case Cover for Apple iPhone 5/5s" : "Premium Slim Snap Case Cover for Apple iPhone 5/5s",
  "Slim Snap Case Cover Matte Finish for Xiaomi Mi 4" : "Slim Snap Case Cover Matte Finish for Xiaomi Mi 4",
  "SL.9.1979 Analog Leather Band Watch" : "SL.9.1979 Analog Leather Band Watch",
  "Sheer Blonde Everlasting Conditioner" : "Sheer Blonde Everlasting Conditioner",
  "SL.9.1346 Analog steel Band Watch" : "SL.9.1346 Analog steel Band Watch",
  "Premium Vinyl Skin Decal Body Wrap for Huawei Honor V8" : "Premium Vinyl Skin Decal Body Wrap for Huawei Honor V8",
  "Slim Snap Case Cover - Bruce Lee for Samsung Galaxy A7 2016" : "Slim Snap Case Cover - Bruce Lee for Samsung Galaxy A7 2016",
  "Premium Slim Snap Case Cover Matte Finish for Sony Xperia Z3" : "Premium Slim Snap Case Cover Matte Finish for Sony Xperia Z3",
  "SL.9.1984 Analog Nylon Band Watch" : "SL.9.1984 Analog Nylon Band Watch",
  "Quatre EDP Set" : "Quatre EDP Set",
  "Premium Vinyl Skin Decal Body Wrap for Apple iPad 1 (1st Gen)" : "Premium Vinyl Skin Decal Body Wrap for Apple iPad 1 (1st Gen)",
  "Pack Of 3 Eucalyptus Air Freshner Card" : "Pack Of 3 Eucalyptus Air Freshner Card",
  "Premium Vinyl Skin Decal Body Wrap for Apple iPad mini 4" : "Premium Vinyl Skin Decal Body Wrap for Apple iPad mini 4",
  "Premium Vinyl Skin Decal Body Wrap for Apple iPad mini 1" : "Premium Vinyl Skin Decal Body Wrap for Apple iPad mini 1",
  "Premium Vinyl Skin Decal Body Wrap for Apple iPad mini 3" : "Premium Vinyl Skin Decal Body Wrap for Apple iPad mini 3",
  "Original Shine Protectant 1gal" : "Original Shine Protectant 1gal",
  "Pavilion x360 15.6-Inch Display, Core i5 Processor/8GBRAM/1TB HDD" : "Pavilion x360 15.6-Inch Display, Core i5 Processor/8GBRAM/1TB HDD",
  "Round Studded Watch - LO-CS-140707" : "Round Studded Watch - LO-CS-140707",
  "Saiph Extrait De Parfum" : "Saiph Extrait De Parfum",
  "Ratchet Tie Down J Hooks 4.5m" : "Ratchet Tie Down J Hooks 4.5m",
  "Semi-Permanent Hair Colour Cream" : "Semi-Permanent Hair Colour Cream",
  "Roadstar Analog Watch - LO-RDS-202" : "Roadstar Analog Watch - LO-RDS-202",
  "Roadstar Analog Watch - LO-RDS-204" : "Roadstar Analog Watch - LO-RDS-204",
  "Roadstar Analog Watch - LO-RDS-205" : "Roadstar Analog Watch - LO-RDS-205",
  "Slim Snap Case Cover - Bruce Lee for Google Pixel XL" : "Slim Snap Case Cover - Bruce Lee for Google Pixel XL",
  "See by Si Belle EDP" : "See by Si Belle EDP",
  "Slim Snap Case Cover Matte Finish for LG G6" : "Slim Snap Case Cover Matte Finish for LG G6",
  "Pink Chiffon Body Mist" : "Pink Chiffon Body Mist",
  "Original Protectant 16oz" : "Original Protectant 16oz",
  "SL.9.1977 Multi Function Leather Band Watch" : "SL.9.1977 Multi Function Leather Band Watch",
  "Paradise Bay EDT" : "Paradise Bay EDT",
  "Slim Snap Case Cover - Angry Birds for Samsung Galaxy A5 2016" : "Slim Snap Case Cover - Angry Birds for Samsung Galaxy A5 2016",
  "Pack Of 3 Hair Oil" : "Pack Of 3 Hair Oil",
  "Signorina EDT" : "Signorina EDT",
  "Slim Snap Case Cover - Angry Birds for Samsung Galaxy A7 2016" : "Slim Snap Case Cover - Angry Birds for Samsung Galaxy A7 2016",
  "Premium Dual Layer Tough Case Cover with Matte Finish for Apple iPhone 5/5s" : "Premium Dual Layer Tough Case Cover with Matte Finish for Apple iPhone 5/5s",
  "Slim Snap Case Cover for Huawei Honor 6" : "Slim Snap Case Cover for Huawei Honor 6",
  "SL.9.917.2.J5 Chronograph Display Leather Band Watch" : "SL.9.917.2.J5 Chronograph Display Leather Band Watch",
  "Slim Snap Case Cover - Angry Birds for OnePlus OnePlus 3/3T" : "Slim Snap Case Cover - Angry Birds for OnePlus OnePlus 3/3T",
  "Premium Dual Layer Tough Case Cover Gloss Finish for Apple iPhone 6/6s" : "Premium Dual Layer Tough Case Cover Gloss Finish for Apple iPhone 6/6s",
  "SL.9.853.4.02 Multi Function Display Steel Band Watch" : "SL.9.853.4.02 Multi Function Display Steel Band Watch",
  "Punky Colour" : "Punky Colour",
  "SL.9.1981 Analog Nylon Band Watch" : "SL.9.1981 Analog Nylon Band Watch",
  "Premium Slim Snap Case Cover Matte Finish for LG G5" : "Premium Slim Snap Case Cover Matte Finish for LG G5",
  "Selfie Expert F1S" : "Selfie Expert F1S",
  "Slim Snap Case Cover - Keep Calm And Eat Shawarma for Samsung Galaxy A3 2016" : "Slim Snap Case Cover - Keep Calm And Eat Shawarma for Samsung Galaxy A3 2016",
  "Slim Snap Case - Street Fighter - Ken for Samsung Galaxy A3 2016" : "Slim Snap Case - Street Fighter - Ken for Samsung Galaxy A3 2016",
  "Ray Metal Chain Watch - WRY-071717" : "Ray Metal Chain Watch - WRY-071717",
  "Slim Snap Case Cover - Bruce Lee for Samsung Galaxy A5 2016" : "Slim Snap Case Cover - Bruce Lee for Samsung Galaxy A5 2016",
  "Piguet Bois Noir EDP" : "Piguet Bois Noir EDP",
  "Set Of 2 Ratchet Tie Down 4.25m" : "Set Of 2 Ratchet Tie Down 4.25m",
  "Secret Romantic Body Mist" : "Secret Romantic Body Mist",
  "Patchouli EDP" : "Patchouli EDP",
  "SL.9.1980 Analog Nylon Band Watch" : "SL.9.1980 Analog Nylon Band Watch",
  "Premium Vinyl Skin Decal Body Wrap for Samsung Galaxy Edge" : "Premium Vinyl Skin Decal Body Wrap for Samsung Galaxy Edge",
  "Pour Homme EDT Miniture" : "Pour Homme EDT Miniture",
  "Passenger Cruise EDT" : "Passenger Cruise EDT",
  "Passenger Cruise EDP" : "Passenger Cruise EDP",
  "Paris Gold Intensitive Aoud EDP" : "Paris Gold Intensitive Aoud EDP",
  "Roadstar Leather Watch - LO-RDS-505" : "Roadstar Leather Watch - LO-RDS-505",
  "Paneria Watch With Additional Strap Alloy - LO-PRN-020207S" : "Paneria Watch With Additional Strap Alloy - LO-PRN-020207S",
  "Protectant Wipes Bonus Pack" : "Protectant Wipes Bonus Pack",
  "Set of 3 Nail Polish" : "Set of 3 Nail Polish",
  "SL.9.1970 Analog Leather Band Watch" : "SL.9.1970 Analog Leather Band Watch",
  "Slim Snap Case Cover - When words fail for Google Pixel XL" : "Slim Snap Case Cover - When words fail for Google Pixel XL",
  "Premium Flip Case Cover for Apple iPhone 6/6s" : "Premium Flip Case Cover for Apple iPhone 6/6s",
  "PU Leather Pull Tab Slip Pouch Case For Apple iPhone 5" : "PU Leather Pull Tab Slip Pouch Case For Apple iPhone 5",
  "Slim Snap Case - Cowhide Leather for Samsung Galaxy A3 2016" : "Slim Snap Case - Cowhide Leather for Samsung Galaxy A3 2016",
  "Premium Dual Layer Tough Case Cover Matte Finish for Apple iPhone 6/6s" : "Premium Dual Layer Tough Case Cover Matte Finish for Apple iPhone 6/6s",
  "Santal Des Indes EDP" : "Santal Des Indes EDP",
  "Premium Dual Layer Tough Case Cover Matte Finish for Samsung Galaxy S6 Edge" : "Premium Dual Layer Tough Case Cover Matte Finish for Samsung Galaxy S6 Edge",
  "Pack Of 3 Vanilla Air Freshner Card" : "Pack Of 3 Vanilla Air Freshner Card",
  "Rolf Flowerbomb Extreme EDP" : "Rolf Flowerbomb Extreme EDP",
  "Opus Series Alloy Watch - LO-OM-II-0202" : "Opus Series Alloy Watch - LO-OM-II-0202",
  "Reflection EDP Spray" : "Reflection EDP Spray",
  "Premium Vinyl Skin Decal Body Wrap for Apple iPad 2 (2011, 2nd Gen)" : "Premium Vinyl Skin Decal Body Wrap for Apple iPad 2 (2011, 2nd Gen)",
  "Signorina Eleganza" : "Signorina Eleganza",
  "Slim Snap Case Cover Matte Finish for Samsung Galaxy J7 2016" : "Slim Snap Case Cover Matte Finish for Samsung Galaxy J7 2016",
  "Silicon Straped Outlander III Watch - LO-OTR-III-0703" : "Silicon Straped Outlander III Watch - LO-OTR-III-0703",
  "Premium Vinyl Skin Decal Body Wrap for Apple iPhone 6s" : "Premium Vinyl Skin Decal Body Wrap for Apple iPhone 6s",
  "Organics Hair Mayonnaise" : "Organics Hair Mayonnaise",
  "Pour L'homme Iii Oud EDT" : "Pour L'homme Iii Oud EDT",
  "Premium Vinyl Skin Decal Body Wrap for HTC One M9" : "Premium Vinyl Skin Decal Body Wrap for HTC One M9",
  "Premium Vinyl Skin Decal Body Wrap for HTC One M8" : "Premium Vinyl Skin Decal Body Wrap for HTC One M8",
  "Pack Of 3 Cool Mist Air Freshner Card" : "Pack Of 3 Cool Mist Air Freshner Card",
  "Orchid Roman Fabric Watch - LO-ORC-020207" : "Orchid Roman Fabric Watch - LO-ORC-020207",
  "Premium Vinyl Skin Decal Body Wrap for Sony Xperia Z3" : "Premium Vinyl Skin Decal Body Wrap for Sony Xperia Z3",
  "Premium Vinyl Skin Decal Body Wrap for Samsung Note 10.1 SM" : "Premium Vinyl Skin Decal Body Wrap for Samsung Note 10.1 SM",
  "Premium Slim Snap Case Cover with Gloss Finish for Apple iPhone 5/5s" : "Premium Slim Snap Case Cover with Gloss Finish for Apple iPhone 5/5s",
  "Premium Vinyl Skin Decal Body Wrap for Samsung Note Pro 12.2 SM" : "Premium Vinyl Skin Decal Body Wrap for Samsung Note Pro 12.2 SM",
  "Penelope Stone Studded Brass Watch - WPNE-060706" : "Penelope Stone Studded Brass Watch - WPNE-060706",
  "Paris Indian Dream EDP" : "Paris Indian Dream EDP",
  "Premium Slim Snap Case Cover with Gloss Finish - Routine Grey for Apple iPhone 5/5s" : "Premium Slim Snap Case Cover with Gloss Finish - Routine Grey for Apple iPhone 5/5s",
  "Premium Dual Layer Tough Case Cover Matte Finish for iPhone 6 Plus/6s Plus" : "Premium Dual Layer Tough Case Cover Matte Finish for iPhone 6 Plus/6s Plus",
  "Slim Snap Case Cover Matte Finish for Apple iPhone 7" : "Slim Snap Case Cover Matte Finish for Apple iPhone 7",
  "Pack Of 3 Wild Berry Air Freshner Card" : "Pack Of 3 Wild Berry Air Freshner Card",
  "Oxford Sleek Casual Brass Watch - MOX-0303" : "Oxford Sleek Casual Brass Watch - MOX-0303",
  "SL.9.1978 Analog Leather Band Watch" : "SL.9.1978 Analog Leather Band Watch",
  "Premium Vinyl Skin Decal Body Wrap for HTC One M9 Plus" : "Premium Vinyl Skin Decal Body Wrap for HTC One M9 Plus",
  "Premium Slim Snap Case Cover with Matte Finish for Apple iPhone 5/5s" : "Premium Slim Snap Case Cover with Matte Finish for Apple iPhone 5/5s",
  "Secret Such A Flirt Body Mist" : "Secret Such A Flirt Body Mist",
  "Slim Snap Case Cover - Angry Birds for Samsung Galaxy A3 2016" : "Slim Snap Case Cover - Angry Birds for Samsung Galaxy A3 2016",
  "Philosykos EDP" : "Philosykos EDP",
  "Premium Dual Layer Tough Case Cover Gloss Finish for iPhone 6 Plus/6s Plus" : "Premium Dual Layer Tough Case Cover Gloss Finish for iPhone 6 Plus/6s Plus",
  "Philosykos EDT" : "Philosykos EDT",
  "Slim Snap Case - Keep Calm And Eat Shawarma for Huawei Honor 6 Plus" : "Slim Snap Case - Keep Calm And Eat Shawarma for Huawei Honor 6 Plus",
  "Private Black Vetiver EDT" : "Private Black Vetiver EDT",
  "Premium Slim Snap Case Gloss Finish for Apple iPhone 6" : "Premium Slim Snap Case Gloss Finish for Apple iPhone 6",
  "Slim Snap Case Cover - Gameboy Colours for Google Pixel" : "Slim Snap Case Cover - Gameboy Colours for Google Pixel",
  "Premium Slim Snap Case Cover Gloss Finish for Samsung Galaxy S5" : "Premium Slim Snap Case Cover Gloss Finish for Samsung Galaxy S5",
  "Signature Metal Chain Brass Watch - WSN-171717" : "Signature Metal Chain Brass Watch - WSN-171717",
  "Premium Dual Layer Tough Case Cover Matte Finish for Apple iPhone 6 Plus/6s Plus" : "Premium Dual Layer Tough Case Cover Matte Finish for Apple iPhone 6 Plus/6s Plus",
  "Premium Slim Snap Case Cover Gloss Finish for Samsung Galaxy S6" : "Premium Slim Snap Case Cover Gloss Finish for Samsung Galaxy S6",
  "Premium Slim Snap Case Cover Matte Finish for LG G3" : "Premium Slim Snap Case Cover Matte Finish for LG G3",
  "Premium Dual Layer Tough Case Cover Matte Finish for Samsung Galaxy S6" : "Premium Dual Layer Tough Case Cover Matte Finish for Samsung Galaxy S6",
  "Premium Slim Snap Case Cover Matte Finish for LG G4" : "Premium Slim Snap Case Cover Matte Finish for LG G4",
  "Slim Snap Case Cover - Spidermark for Huawei Honor 6 Plus" : "Slim Snap Case Cover - Spidermark for Huawei Honor 6 Plus",
  "Premium Slim Snap Case Cover Gloss Finish for Samsung Galaxy Note 4" : "Premium Slim Snap Case Cover Gloss Finish for Samsung Galaxy Note 4",
  "Premium Slim Snap Case Cover Gloss Finish for Samsung Galaxy Note 5" : "Premium Slim Snap Case Cover Gloss Finish for Samsung Galaxy Note 5",
  "Set Of 4 The One EDP Miniture" : "Set Of 4 The One EDP Miniture",
  "Original Beard Wax" : "Original Beard Wax",
  "Premium Vinyl Skin Decal Body Wrap for LG Google Nexus 5" : "Premium Vinyl Skin Decal Body Wrap for LG Google Nexus 5",
  "Slim Snap Case Cover Matte Finish for Google Nexus 6" : "Slim Snap Case Cover Matte Finish for Google Nexus 6",
  "Portable Boombox 3.0 Music Bluetooth Speaker" : "Portable Boombox 3.0 Music Bluetooth Speaker",
  "Pack Of 3 Lavender Air Freshner Card" : "Pack Of 3 Lavender Air Freshner Card",
  "S15 Mobile Phone With 10000mAh Power Bank Battery" : "S15 Mobile Phone With 10000mAh Power Bank Battery",
  "Premium Slim Snap Case Cover Gloss Finish for Apple iPhone 6/6s" : "Premium Slim Snap Case Cover Gloss Finish for Apple iPhone 6/6s",
  "Premium Flip Case Cover for Apple iPhone 6 Plus/6s Plus" : "Premium Flip Case Cover for Apple iPhone 6 Plus/6s Plus",
  "Redmi Note 2" : "Redmi Note 2",
  "Premium Vinyl Skin Decal Body Wrap for HTC One A9" : "Premium Vinyl Skin Decal Body Wrap for HTC One A9",
  "Orchid Roman Fabric Watch - LO-ORC-010207" : "Orchid Roman Fabric Watch - LO-ORC-010207",
  "Pavilion 15t 15.6-Inch Display, Core i7 Processor/16GBRAM/1TB HDD/4GB NVIDIA Graphic Card" : "Pavilion 15t 15.6-Inch Display, Core i7 Processor/16GBRAM/1TB HDD/4GB NVIDIA Graphic Card",
  "Premium Vinyl Skin Decal Body Wrap for Sony Xperia X Performance" : "Premium Vinyl Skin Decal Body Wrap for Sony Xperia X Performance",
  "Portable Boombox 3.0 Music Bluetooth  Speaker" : "Portable Boombox 3.0 Music Bluetooth  Speaker",
  "Slim Snap Case Cover Matte Finish for Samsung Galaxy S8" : "Slim Snap Case Cover Matte Finish for Samsung Galaxy S8",
  "Premium Slim Snap Case Gloss Finish for Samsung Galaxy S6 Edge" : "Premium Slim Snap Case Gloss Finish for Samsung Galaxy S6 Edge",
  "Slim Snap Case Cover - Keep Calm And Eat Shawarma for OnePlus OnePlus 3/3T" : "Slim Snap Case Cover - Keep Calm And Eat Shawarma for OnePlus OnePlus 3/3T",
  "Outlast Trim And Plastic Restorer 8oz" : "Outlast Trim And Plastic Restorer 8oz",
  "Opus II Watch - LO-OPUS-II-0303W" : "Opus II Watch - LO-OPUS-II-0303W",
  "Slim Snap Case Cover for Samsung Galaxy A7 2016" : "Slim Snap Case Cover for Samsung Galaxy A7 2016",
  "Premium Vinyl Skin Decal Body Wrap for OnePlus OnePlus One" : "Premium Vinyl Skin Decal Body Wrap for OnePlus OnePlus One",
  "Premium Vinyl Skin Decal Body Wrap for HTC One Max" : "Premium Vinyl Skin Decal Body Wrap for HTC One Max",
  "Premium Slim Snap Case Cover Matte Finish for Samsung Galaxy S7 Edge" : "Premium Slim Snap Case Cover Matte Finish for Samsung Galaxy S7 Edge",
  "Premium Vinyl Skin Decal Body Wrap for LG G4" : "Premium Vinyl Skin Decal Body Wrap for LG G4",
  "Premium Vinyl Skin Decal Body Wrap for LG G5" : "Premium Vinyl Skin Decal Body Wrap for LG G5",
  "Piguet Oud Divin EDP" : "Piguet Oud Divin EDP",
  "Premium Vinyl Skin Decal Body Wrap for LG G2" : "Premium Vinyl Skin Decal Body Wrap for LG G2",
  "Retro 10 Analog Watch - LO-RET-1003" : "Retro 10 Analog Watch - LO-RET-1003",
  "Retro 10 Analog Watch - LO-RET-1002" : "Retro 10 Analog Watch - LO-RET-1002",
  "Retro 10 Analog Watch - LO-RET-1001" : "Retro 10 Analog Watch - LO-RET-1001",
  "Premium Dual Layer Tough Case Cover Matte Finish for Samsung Galaxy Note 4" : "Premium Dual Layer Tough Case Cover Matte Finish for Samsung Galaxy Note 4",
  "Selfie Monopod Stick with Remote for Mobile Phones" : "Selfie Monopod Stick with Remote for Mobile Phones",
  "Premium Vinyl Skin Decal Body Wrap for Apple iPhone 7 Plus" : "Premium Vinyl Skin Decal Body Wrap for Apple iPhone 7 Plus",
  "Secret Rush Body Mist" : "Secret Rush Body Mist",
  "Slim Snap Case Cover - Gameboy Colours for Samsung Galaxy A7 2016" : "Slim Snap Case Cover - Gameboy Colours for Samsung Galaxy A7 2016",
  "Premium Vinyl Skin Decal Body Wrap for Apple iPad Air" : "Premium Vinyl Skin Decal Body Wrap for Apple iPad Air",
  "Premium Vinyl Skin Decal Body Wrap for Apple iPhone 5s" : "Premium Vinyl Skin Decal Body Wrap for Apple iPhone 5s",
  "Parfumes Splendor Ocean EDP" : "Parfumes Splendor Ocean EDP",
  "Premium Vinyl Skin Decal Body Wrap for Apple iPad (2012, 3rd & 4th gen)" : "Premium Vinyl Skin Decal Body Wrap for Apple iPad (2012, 3rd & 4th gen)",
  "SL.9.1982 Analog Nylon Band Watch" : "SL.9.1982 Analog Nylon Band Watch",
  "Premium Dual Layer Tough Case Cover Matte Finish for Apple iPhone 5/5s/SE" : "Premium Dual Layer Tough Case Cover Matte Finish for Apple iPhone 5/5s/SE",
  "Shield Car Wash 520ml" : "Shield Car Wash 520ml",
  "S2 Pro" : "S2 Pro",
  "Premium Vinyl Skin Decal Body Wrap for Apple iPhone 6s Plus" : "Premium Vinyl Skin Decal Body Wrap for Apple iPhone 6s Plus",
  "Slim Snap Case Cover Matte Finish for Samsung Galaxy S8 Plus" : "Slim Snap Case Cover Matte Finish for Samsung Galaxy S8 Plus",
  "Rodriguez Fleur Musc EDP" : "Rodriguez Fleur Musc EDP",
  "Royal Edition Femme EDP" : "Royal Edition Femme EDP",
  "Rive Gauche Pour Femme EDT" : "Rive Gauche Pour Femme EDT",
  "Piguet Fracas EDP" : "Piguet Fracas EDP",
  "Premium Slim Snap Case Cover Matte Finish for Samsung Galaxy Note 7" : "Premium Slim Snap Case Cover Matte Finish for Samsung Galaxy Note 7",
  "ROG 17.3-Inch Display, Core i7 Processor/16GBRAM/1TB+128GB SSD Hybrid Drive/4GB NVIDIA Graphic Card" : "ROG 17.3-Inch Display, Core i7 Processor/16GBRAM/1TB+128GB SSD Hybrid Drive/4GB NVIDIA Graphic Card",
  "Premium Slim Snap Case Cover Matte Finish for Samsung Galaxy Note 5" : "Premium Slim Snap Case Cover Matte Finish for Samsung Galaxy Note 5",
  "Premium Slim Snap Case Cover Matte Finish for Samsung Galaxy Note 4" : "Premium Slim Snap Case Cover Matte Finish for Samsung Galaxy Note 4",
  "Slim Snap Case Cover - Angry Birds for Google Pixel XL" : "Slim Snap Case Cover - Angry Birds for Google Pixel XL",
  "Slim Snap Case Cover Matte Finish for Samsung Galaxy J5 2016" : "Slim Snap Case Cover Matte Finish for Samsung Galaxy J5 2016",
  "Premium Slim Snap Case Cover Matte Finish for Samsung Galaxy S6 Edge" : "Premium Slim Snap Case Cover Matte Finish for Samsung Galaxy S6 Edge",
  "Slim Snap Case Cover Matte Finish for Google Nexus 6P" : "Slim Snap Case Cover Matte Finish for Google Nexus 6P",
  "Oud Et Oriental EDP" : "Oud Et Oriental EDP",
  "Pack Of 12 Star Ball 40+" : "Pack Of 12 Star Ball 40+",
  "Premium Vinyl Skin Decal Body Wrap for Nokia Lumia 920" : "Premium Vinyl Skin Decal Body Wrap for Nokia Lumia 920",
  "Premium Dual Layer Tough Case Gloss Finish for Apple iPhone 6" : "Premium Dual Layer Tough Case Gloss Finish for Apple iPhone 6",
  "SL.9.1356 Multi Function Stainless Steel Band Watch" : "SL.9.1356 Multi Function Stainless Steel Band Watch",
  "Premium Vinyl Skin Decal Body Wrap for Nokia Lumia 1020" : "Premium Vinyl Skin Decal Body Wrap for Nokia Lumia 1020",
  "S56 Mobile Phone With 12800mAh Power Bank Battery" : "S56 Mobile Phone With 12800mAh Power Bank Battery",
  "Portable Boombox Music Double Speaker" : "Portable Boombox Music Double Speaker",
  "Papillon Chenille Apron" : "Papillon Chenille Apron",
  "Shea Butter Coconut Curling Cream" : "Shea Butter Coconut Curling Cream",
  "Paneria Watch With Additional Strap Alloy - LO-PRN-030307S" : "Paneria Watch With Additional Strap Alloy - LO-PRN-030307S",
  "Premium Slim Snap Case Cover Matte Finish for Samsung Galaxy S6" : "Premium Slim Snap Case Cover Matte Finish for Samsung Galaxy S6",
  "Premium Slim Snap Case Cover Matte Finish for Samsung Galaxy S7" : "Premium Slim Snap Case Cover Matte Finish for Samsung Galaxy S7",
  "Premium Slim Snap Case Cover Matte Finish for Samsung Galaxy S5" : "Premium Slim Snap Case Cover Matte Finish for Samsung Galaxy S5",
  "Premium Vinyl Skin Decal Body Wrap for Apple iPhone 6" : "Premium Vinyl Skin Decal Body Wrap for Apple iPhone 6",
  "Premium Vinyl Skin Decal Body Wrap for Apple iPhone 7" : "Premium Vinyl Skin Decal Body Wrap for Apple iPhone 7",
  "Premium Vinyl Skin Decal Body Wrap for Apple iPhone 4" : "Premium Vinyl Skin Decal Body Wrap for Apple iPhone 4",
  "Premium Vinyl Skin Decal Body Wrap for Apple iPhone 5" : "Premium Vinyl Skin Decal Body Wrap for Apple iPhone 5",
  "Rossetto EDP" : "Rossetto EDP",
  "SL.9.956.2.J1 Multi Function Display Steel Band Watch" : "SL.9.956.2.J1 Multi Function Display Steel Band Watch",
  "Rose Greedy EDP" : "Rose Greedy EDP",
  "Premium Vinyl Skin Decal Body Wrap for Samsung Galaxy S5" : "Premium Vinyl Skin Decal Body Wrap for Samsung Galaxy S5",
  "Premium Vinyl Skin Decal Body Wrap for Samsung Galaxy S4" : "Premium Vinyl Skin Decal Body Wrap for Samsung Galaxy S4",
  "Premium Vinyl Skin Decal Body Wrap for Samsung Galaxy S7" : "Premium Vinyl Skin Decal Body Wrap for Samsung Galaxy S7",
  "Premium Vinyl Skin Decal Body Wrap for Samsung Galaxy S6" : "Premium Vinyl Skin Decal Body Wrap for Samsung Galaxy S6",
  "Premium Vinyl Skin Decal Body Wrap for Samsung Galaxy S3" : "Premium Vinyl Skin Decal Body Wrap for Samsung Galaxy S3",
  "Slim Snap Case Cover for OnePlus OnePlus 3/3T" : "Slim Snap Case Cover for OnePlus OnePlus 3/3T",
  "Premium Slim Snap Case Cover Matte Finish for LG V10" : "Premium Slim Snap Case Cover Matte Finish for LG V10",
  "Scherrer 2 EDT" : "Scherrer 2 EDT",
  "Pure Multipurpose Organic Argan Oil" : "Pure Multipurpose Organic Argan Oil",
  "Premium Slim Snap Case Cover Gloss Finish for Apple iPhone 6 Plus" : "Premium Slim Snap Case Cover Gloss Finish for Apple iPhone 6 Plus",
  "SL.9.1973 Analog Mesh Band Watch" : "SL.9.1973 Analog Mesh Band Watch",
  "Slim Snap Case Cover Matte Finish for LG V20" : "Slim Snap Case Cover Matte Finish for LG V20",
  "Shalimar EDP" : "Shalimar EDP",
  "Oud Stars Gao EDP" : "Oud Stars Gao EDP",
  "Premium Dual Layer Tough Case Cover Gloss Finish for Apple iPhone 6" : "Premium Dual Layer Tough Case Cover Gloss Finish for Apple iPhone 6",
  "SL.9.1969 Analog Leather Band Watch" : "SL.9.1969 Analog Leather Band Watch",
  "Round Studded Watch - LO-CS-020707" : "Round Studded Watch - LO-CS-020707",
  "Premium Vinyl Skin Decal Body Wrap for Google Nexus 5X" : "Premium Vinyl Skin Decal Body Wrap for Google Nexus 5X",
  "S17 Mobile Phone With 10000mAh Power Bank Battery" : "S17 Mobile Phone With 10000mAh Power Bank Battery",
  "Premium Dual Layer Tough Case Cover Gloss Finish for Apple iPhone 6 Plus/6s Plus" : "Premium Dual Layer Tough Case Cover Gloss Finish for Apple iPhone 6 Plus/6s Plus",
  "SL.9.1984.3.09 Analog Display Nylon Band Watch" : "SL.9.1984.3.09 Analog Display Nylon Band Watch",
  "Pokemon Shape USB Flash Memory Drive" : "Pokemon Shape USB Flash Memory Drive",
  "Purple Amethyst EDP" : "Purple Amethyst EDP",
  "Reve Enchante EDP" : "Reve Enchante EDP",
  "Paul Frank Case For iPad Mini" : "Paul Frank Case For iPad Mini",
  "Oud Immortel EDP" : "Oud Immortel EDP",
  "Signorina Misteriosa EDP Set" : "Signorina Misteriosa EDP Set",
  "Slim Snap Case Cover for Huawei Honor 4X" : "Slim Snap Case Cover for Huawei Honor 4X",
  "Renewing Moroccan Argan Oil" : "Renewing Moroccan Argan Oil",
  "Shield For Wheels 300ml" : "Shield For Wheels 300ml",
  "Outboard Motor Padlock" : "Outboard Motor Padlock",
  "Slim Snap Case Cover for Samsung Galaxy A3 2016" : "Slim Snap Case Cover for Samsung Galaxy A3 2016",
  "Premium Vinyl Skin Decal Body Wrap for HTC Desire 530" : "Premium Vinyl Skin Decal Body Wrap for HTC Desire 530",
  "Set Of 4 Ratchet Tie Down 4.25m" : "Set Of 4 Ratchet Tie Down 4.25m",
  "Slim Snap Case Cover - Fighter Bruce Lee for OnePlus OnePlus 3/3T" : "Slim Snap Case Cover - Fighter Bruce Lee for OnePlus OnePlus 3/3T",
  "Premium Slim Snap Case Cover Gloss Finish for Apple iPhone 6" : "Premium Slim Snap Case Cover Gloss Finish for Apple iPhone 6",
  "Slim Snap Case Cover - I Love Pizza for OnePlus OnePlus 3/3T" : "Slim Snap Case Cover - I Love Pizza for OnePlus OnePlus 3/3T",
  "S23 Mobile Phone With 10000mAh Power Bank Battery" : "S23 Mobile Phone With 10000mAh Power Bank Battery",
  "SL.9.955.3.07 Analog Display Stainless Steel Band Watch" : "SL.9.955.3.07 Analog Display Stainless Steel Band Watch",
  "Premium Slim Snap Case Cover Matte Finish for Samsung Galaxy S6 Edge Plus" : "Premium Slim Snap Case Cover Matte Finish for Samsung Galaxy S6 Edge Plus",
  "Skeleton Finish Invictus 5 Watch - LO-INC-502" : "Skeleton Finish Invictus 5 Watch - LO-INC-502",
  "Skeleton Finish Invictus 5 Watch - LO-INC-501" : "Skeleton Finish Invictus 5 Watch - LO-INC-501",
  "Secret Aqua Kiss Body Mist" : "Secret Aqua Kiss Body Mist",
  "Premium Dual Layer Tough Case Cover - When Words Fail for Apple iPhone 5/5s" : "Premium Dual Layer Tough Case Cover - When Words Fail for Apple iPhone 5/5s",
  "Slim Snap Case Cover - Tibute to Bruce Lee for OnePlus OnePlus 3/3T" : "Slim Snap Case Cover - Tibute to Bruce Lee for OnePlus OnePlus 3/3T",
  "Premium Vinyl Skin Decal Body Wrap for Samsung Galaxy S4 Mini" : "Premium Vinyl Skin Decal Body Wrap for Samsung Galaxy S4 Mini",
  "Organic Curl Enhancing Smoothie" : "Organic Curl Enhancing Smoothie",
  "SL.9.1350 Analog Resin Band Watch" : "SL.9.1350 Analog Resin Band Watch",
  "Pro Slate 8 7.86-Inch Display, OMAP Processor/2GBRAM/16GB Flash/Integrated Graphics" : "Pro Slate 8 7.86-Inch Display, OMAP Processor/2GBRAM/16GB Flash/Integrated Graphics",
  "Slim Snap Case Cover - Gameboy Colour for Samsung Galaxy A3 2016" : "Slim Snap Case Cover - Gameboy Colour for Samsung Galaxy A3 2016",
  "Premium Vinyl Skin Decal Body Wrap for Apple iPad mini 2 Retina" : "Premium Vinyl Skin Decal Body Wrap for Apple iPad mini 2 Retina",
  "OT 2012D" : "OT 2012D",
  "SL.9.1348 Multi Function Stainless Steel Band Watch" : "SL.9.1348 Multi Function Stainless Steel Band Watch",
  "Quatre Femme EDP" : "Quatre Femme EDP",
  "Premium Vinyl Skin Decal Body Wrap for LG V10" : "Premium Vinyl Skin Decal Body Wrap for LG V10",
  "Redmi Note 4X" : "Redmi Note 4X",
  "Piguet Futur EDP" : "Piguet Futur EDP",
  "Premium Vinyl Skin Decal Body Wrap for Blackberry Q10" : "Premium Vinyl Skin Decal Body Wrap for Blackberry Q10",
  "Slim Snap Case Cover Matte Finish for Apple iPhone 7 Plus" : "Slim Snap Case Cover Matte Finish for Apple iPhone 7 Plus",
  "Premium Vinyl Skin Decal Body Wrap for Samsung Galaxy S7 Edge" : "Premium Vinyl Skin Decal Body Wrap for Samsung Galaxy S7 Edge",
  "Slim Snap Case Cover for Google Pixel" : "Slim Snap Case Cover for Google Pixel",
  "Redmi 4A" : "Redmi 4A",
  "Premium Slim Snap Case for Samsung Galaxy S6" : "Premium Slim Snap Case for Samsung Galaxy S6",
  "Oud Du Jour EDP" : "Oud Du Jour EDP",
  "Redmi 4X" : "Redmi 4X",
  "Paradise EDT" : "Paradise EDT",
  "Premium Dual Layer Tough Case Cover Gloss Finish for iPhone 6 Plus" : "Premium Dual Layer Tough Case Cover Gloss Finish for iPhone 6 Plus",
  "Premium Slim Snap Case Cover Matte Finish for Apple iPhone 6 Plus" : "Premium Slim Snap Case Cover Matte Finish for Apple iPhone 6 Plus",
  "Paneria Watch With Additional Strap Alloy - LO-PRN-070907S" : "Paneria Watch With Additional Strap Alloy - LO-PRN-070907S",
  "SL.9.1974 Analog Mesh Band Watch" : "SL.9.1974 Analog Mesh Band Watch",
  "Perles EDP" : "Perles EDP",
  "Premium USB C to USB Adapter For MacBook 12-inch" : "Premium USB C to USB Adapter For MacBook 12-inch",
  "Premium Vinyl Skin Decal Body Wrap for Apple iPhone 6 Plus" : "Premium Vinyl Skin Decal Body Wrap for Apple iPhone 6 Plus",
  "Retractable Cable Lock Assorted" : "Retractable Cable Lock Assorted",
  "Premium Dual Layer Tough Case Cover Gloss Finish for Samsung Galaxy S6 Edge" : "Premium Dual Layer Tough Case Cover Gloss Finish for Samsung Galaxy S6 Edge",
  "Oud De Carthage EDP" : "Oud De Carthage EDP",
  "Slim Snap Case Cover Matte Finish for Samsung Galaxy Note 7" : "Slim Snap Case Cover Matte Finish for Samsung Galaxy Note 7",
  "Roadstar Classic Watch - LO-RDS-405" : "Roadstar Classic Watch - LO-RDS-405",
  "Premium Slim Snap Case Cover with Gloss Finish for Apple iPhone 5/5s/SE" : "Premium Slim Snap Case Cover with Gloss Finish for Apple iPhone 5/5s/SE",
  "Signorina Misteriosa EDP" : "Signorina Misteriosa EDP",
  "Rumeur 2 Rose" : "Rumeur 2 Rose",
  "Slim Snap Case Cover - Convergence for OnePlus OnePlus 3/3T" : "Slim Snap Case Cover - Convergence for OnePlus OnePlus 3/3T",
  "Slim Snap Case Cover Matte Finish for Google Nexus 5X" : "Slim Snap Case Cover Matte Finish for Google Nexus 5X",
  "Premium Vinyl Skin Decal Body Wrap for Samsung Galaxy S6 Edge" : "Premium Vinyl Skin Decal Body Wrap for Samsung Galaxy S6 Edge"
}